rtl/ram.v
module ram #(parameter words = 65536)
(
    input clk,
    input [31:0] addr,
    input read,
    input [3:0] write,
    input [31:0] DATA_IN,
    output reg [31:0] DATA_OUT
);
reg [31:0] mem [0:words-1];
wire [31:0] addrWords = {2'd0,addr[31:2]};

always@(*) begin
    DATA_OUT = mem[addrWords];
end
/*
always @(posedge clk) begin
    if(read) DATA_OUT <= mem[addrWords];
end
*/
always @(posedge clk) begin
    if(write[0]) mem[addrWords][7:0] <= DATA_IN[7:0];
    if(write[1]) mem[addrWords][15:8] <= DATA_IN[15:8];
    if(write[2]) mem[addrWords][23:16] <= DATA_IN[23:16];
    if(write[3]) mem[addrWords][31:24] <= DATA_IN[31:24];
end

endmodule

rtl/alu.v
module alu(
    input [31:0] rs1_data,
    input [31:0] rs2_data,
    input [3:0] aluSel,
    output reg [31:0] alu_out
);
wire signed [31:0] rs1_singed = rs1_data;
wire signed [31:0] rs2_singed = rs2_data;

parameter [3:0] AND = 4'd0,
                OR  = 4'd1,
                ADD = 4'd2,
                SUB = 4'd3,
                SLT = 4'd4,
                XOR = 4'd5,
                SLL = 4'd6,
                SLTU= 4'd7,
                SRL = 4'd8,
                SRA = 4'd9,
                MUL = 4'd10,
                MULH= 4'd11,
                MULHU=4'd12,
                NONE = 4'd13,
                RS1 = 4'd14;


always@(*) begin
    case(aluSel)
    AND: alu_out = rs1_data & rs2_data;
    OR : alu_out = rs1_data | rs2_data;
    ADD: alu_out = rs1_data + rs2_data;
    SUB: alu_out = rs1_data - rs2_data;
    SLT: alu_out = (rs1_singed < rs2_singed) ? 32'd1 : 32'd0;
    XOR: alu_out = rs1_data ^ rs2_data;
    SLL: alu_out = rs1_data << rs2_data[4:0];
    SLTU: alu_out = (rs1_data < rs2_data) ? 32'd1 : 32'd0;
    SRL: alu_out = rs1_data >> rs2_data[4:0];
    SRA: alu_out = rs1_singed >> rs2_data[4:0];
    NONE: alu_out = 32'd0;
    RS1: alu_out = rs1_data;
    default: alu_out = 32'd0;
    endcase
end

endmodule

rtl/regfile.v
module regfile(
    input clk,
    input rst,
    input [4:0] rs1_addr,
    input [4:0] rs2_addr,
    input [4:0] rd_addr, //write addr
    input [31:0] rd_data,
    input rd_write,
    output wire [31:0] rs1_data,rs2_data
);

reg [31:0] regFile [31:1];

assign rs1_data = (rs1_addr == 5'd0) ? 32'd0 : regFile[rs1_addr];
assign rs2_data = (rs2_addr == 5'd0) ? 32'd0 : regFile[rs2_addr];

integer i;
always@(posedge clk or posedge rst) begin
    if(rst) begin
        for(i=1;i<=31;i=i+1) begin
            regFile[i] <= 32'd0;
        end
    end
    else begin
        if(rd_write && rd_addr != 5'd0) begin
            regFile[rd_addr] <= rd_data;
        end
    end
end

endmodule

rtl/PC.v
module PC(
    input clk,
    input rst,
    input [31:0] next_pc,
    output reg [31:0] pc
);

always@(posedge clk or posedge rst) begin
    if(rst) pc <= 32'd0;
    else pc <= next_pc;
end

endmodule

rtl/control.v
module control(
    input [6:0] opcode,
    input [2:0] funct3,
    input [6:0] funct7,
    output wire instr_mem_read,
    output reg data_mem_read,
    output reg [3:0] data_mem_write,
    output reg rd_write,

    output reg [3:0] aluSel,
    output reg aluSrc1Sel,
    output reg [1:0] aluSrc2Sel,
    output reg [1:0] wbSel,
    output reg [2:0] pcSel
);
assign instr_mem_read = 1'd1;

parameter [3:0] AND = 4'd0,
                OR  = 4'd1,
                ADD = 4'd2,
                SUB = 4'd3,
                SLT = 4'd4,
                XOR = 4'd5,
                SLL = 4'd6,
                SLTU= 4'd7,
                SRL = 4'd8,
                SRA = 4'd9,
                MUL = 4'd10,
                MULH= 4'd11,
                MULHU=4'd12,
                NONE = 4'd13,
                RS1 = 4'd14;

always@(*) begin
    
    case(opcode)
        7'b0110011: begin //R type
            aluSrc1Sel = 1'd0;
            aluSrc2Sel = 2'd0;
            data_mem_read = 1'd0;
            data_mem_write = 4'd0;
            wbSel = 2'd0;
            pcSel = 3'd0;
            rd_write = 1'd1;
            case(funct3)
                3'b000: begin 
                    case(funct7) 
                        7'b0000000: aluSel = ADD;
                        7'b0100000: aluSel = SUB;
                        default: aluSel = NONE;
                    endcase
                end
                3'b001: begin
                    case(funct7) 
                        7'b0000000: aluSel = SLL;
                        default: aluSel = NONE;
                    endcase
                end
                3'b010: begin
                    case(funct7) 
                        7'b0000000: aluSel = SLT;
                        default: aluSel = NONE;
                    endcase
                end
                3'b011: begin
                    case(funct7) 
                        7'b0000000: aluSel = SLTU;
                        default: aluSel = NONE;
                    endcase
                end
                3'b100: begin
                    case(funct7) 
                        7'b0000000: aluSel = XOR;
                        default: aluSel = NONE;
                    endcase
                end
                3'b101: begin
                    case(funct7) 
                        7'b0000000: aluSel = SRL;
                        7'b0100000: aluSel = SRA;
                        default: aluSel = NONE;
                    endcase
                end
                3'b110: begin
                    case(funct7) 
                        7'b0000000: aluSel = OR;
                        default: aluSel = NONE;
                    endcase
                end
                3'b111: begin
                    case(funct7) 
                        7'b0000000: aluSel = AND;
                        default: aluSel = NONE;
                    endcase
                end
                default: aluSel = NONE;
            endcase
        end
        7'b0000011: begin //I-type
        end
        7'b0010011: begin //I-type
            aluSrc1Sel = 1'd0;
            aluSrc2Sel = 2'd2;
            data_mem_read = 1'd0;
            data_mem_write = 4'b0000;
            wbSel = 2'd0;
            pcSel = 3'd0;
            case(funct3)
                3'b000: aluSel = ADD;
                default: aluSel = ADD;
            endcase
            rd_write = 1'd1;
        end
        7'b1100111: begin //I-type
        end
        7'b0100011: begin //S-type
            aluSrc1Sel = 1'd0;
            aluSrc2Sel = 2'd1;
            data_mem_read = 1'd0;
            data_mem_write = 4'b1111;
            wbSel = 2'd1;
            pcSel = 3'd0;
            aluSel = ADD;
            rd_write = 1'd0;
        end
        7'b1100011: begin //B-type
        end
        7'b0010111: begin //U-type
        end
        7'b0110111: begin //U-type
            aluSrc1Sel = 1'd1;
            aluSrc2Sel = 2'd0;
            data_mem_read = 1'd0;
            data_mem_write = 4'd0;
            wbSel = 2'd0;
            pcSel = 3'd0;
            aluSel = RS1;
            rd_write = 1'd1;
        end
        7'b1101111: begin //I-type
        end
        default: begin
            data_mem_read = 1'd0;
            data_mem_write = 4'd0;
            aluSel = NONE;
            aluSrc1Sel = 1'd0;
            aluSrc2Sel = 2'd0;
            wbSel = 2'd0;
            pcSel = 3'd0;
            rd_write = 1'd0;
        end
    endcase
end

endmodule

rtl/CPU.v
module CPU(
    input clk,
    input rst,
    output wire [31:0] instr_mem_addr,
    output wire instr_mem_read,
    input [31:0] instr_mem_data_r,
    output [31:0]data_mem_addr,
    output wire data_mem_read,
    output wire [3:0] data_mem_write,
    input [31:0] data_mem_data_r,
    output [31:0] data_mem_data_w 
);


wire [31:0] I_type_imm = {20'd0,instr_mem_data_r[31:20]};
wire [31:0] S_type_imm = {20'd0,instr_mem_data_r[31:25],instr_mem_data_r[11:7]};

wire [31:0] S_type_imm_signed_extend = {{20{instr_mem_data_r[31]}},instr_mem_data_r[31:25],instr_mem_data_r[11:7]};
wire [31:0] I_type_imm_signed_extend = {{20{instr_mem_data_r[31]}},instr_mem_data_r[31:20]};
wire [19:0] U_type_imm = instr_mem_data_r[31:12];

//declare

//control
wire [3:0] aluSel;
wire aluSrc1Sel;
wire [1:0] aluSrc2Sel;
wire [1:0] wbSel;
wire [2:0] pcSel;
wire rd_write;
//pc
wire [31:0] pc;
wire [31:0] next_pc;
wire [31:0] pc_add_4 = instr_mem_addr + 32'd4;
//regfile
wire [31:0] rs1_data,
            rs2_data;
reg [31:0] rd_data;
//alu
wire [31:0] alu_out;
wire [31:0] alu_rs1;
reg [31:0] alu_rs2;

//control
control control_inst(
    .opcode(instr_mem_data_r[6:0]),
    .funct3(instr_mem_data_r[14:12]),
    .funct7(instr_mem_data_r[31:25]),
    .instr_mem_read(instr_mem_read),
    .data_mem_read(data_mem_read),
    .data_mem_write(data_mem_write),
    .rd_write (rd_write),
    .aluSel(aluSel),
    .aluSrc1Sel(aluSrc1Sel),
    .aluSrc2Sel(aluSrc2Sel),
    .wbSel(wbSel),
    .pcSel(pcSel)
);

//PC
assign instr_mem_addr = pc;
//PC mux
assign next_pc = pc_add_4;
PC PC_inst(
    .clk (clk),
    .rst (rst),
    .next_pc(next_pc),
    .pc(pc)
);



//regfile
always@(*) begin
    case(wbSel)
    2'd0: rd_data = alu_out;
    2'd1: rd_data = data_mem_data_r;
    2'd2: rd_data = pc_add_4; 
    endcase
end

regfile regfile_inst(
    .clk (clk),
    .rst (rst),
    .rs1_addr (instr_mem_data_r[19:15]),
    .rs2_addr (instr_mem_data_r[24:20]),
    .rd_addr (instr_mem_data_r[11:7]),
    .rd_data (rd_data),
    .rd_write (rd_write),
    .rs1_data (rs1_data),
    .rs2_data (rs2_data)
);

//alu
assign alu_rs1 = (aluSrc1Sel == 1'd0) ? rs1_data : {U_type_imm,12'd0};
always@(*) begin
    case (aluSrc2Sel)
        2'd0: alu_rs2 = rs2_data;
        2'd1: alu_rs2 = S_type_imm_signed_extend;
        2'd2: alu_rs2 = I_type_imm_signed_extend;
        2'd3: alu_rs2 = pc;
    endcase
end

alu alu_inst(
    .rs1_data(alu_rs1),
    .rs2_data(alu_rs2),
    .aluSel(aluSel),
    .alu_out(alu_out)
);

//data mem
assign data_mem_addr = alu_out;
assign data_mem_data_w = rs2_data;


endmodule

rtl/top.v
module top #(parameter memWords = 100)
(
    input clk, 
    input rst
);

wire [31:0] instr_mem_addr;
wire instr_mem_read;
wire [31:0] instr_mem_data_r;

wire [31:0] data_mem_addr;
wire data_mem_read;
wire [3:0] data_mem_write;
wire [31:0] data_mem_data_r;
wire [31:0] data_mem_data_w;

CPU riscv (
    .clk        (clk),
    .rst        (rst),
    .instr_mem_addr (instr_mem_addr),
    .instr_mem_read (instr_mem_read),
    .instr_mem_data_r (instr_mem_data_r),
    .data_mem_addr (data_mem_addr),
    .data_mem_read (data_mem_read),
    .data_mem_write (data_mem_write),
    .data_mem_data_r (data_mem_data_r),
    .data_mem_data_w (data_mem_data_w)
);  

ram #(.words(memWords))IM(
    .clk        (clk),
    .addr       (instr_mem_addr),
    .read       (instr_mem_read),
    .write      (4'b0),
    .DATA_IN    (32'b0),
    .DATA_OUT   (instr_mem_data_r)
);
ram #(.words(memWords)) DM(
    .clk        (clk),
    .addr       (data_mem_addr),
    .read       (data_mem_read),
    .write      (data_mem_write),
    .DATA_IN    (data_mem_data_w),
    .DATA_OUT   (data_mem_data_r)
);


endmodule

sim/tb.sv
`define CYCLE 10
`define END 1000
//`define instr "add"
`define HexPath {"./asm/",`instr,"/",`instr,".hex"} 
`define SigPath {"./asm/",`instr,"/",`instr,".sig.dat.hex"} 

module test #(parameter Path = "./asm/add/add.hex");

reg clk,rst;
reg [31:0] resultMem [0:255];
top #(.memWords(100)) dut(
    .clk(clk),
    .rst(rst)
);

int fd,resultLen=0,i=0,error=0;
initial begin
    $readmemh(`HexPath,dut.IM.mem);
    $readmemh(`HexPath,dut.DM.mem);
    fd = $fopen(`SigPath,"r");
   // $display("***%s***",`instr);
    do begin
        $fscanf(fd,"%h",resultMem[resultLen]);
        if(!$feof(fd)) resultLen = resultLen +1;
    end while (!$feof(fd));
end

always #(`CYCLE/2) clk = ~clk;

initial begin
    `ifdef iverilog
        $dumpfile("./test.vcd");
        $dumpvars;
    `else
        $fsdbDumpfile("./test.fsdb");
        $fsdbDumpvars;
        $fsdbDumpMDA;
    `endif 
    
    #(`END) 
    for(i=0;i<resultLen;i++) begin
        if(resultMem[i] == dut.DM.mem[32'h40+i]) begin
            $display("correc, %h",resultMem[i]);
        end
        else begin
            $display("error , %d %h != %h (expected)",i,dut.DM.mem[32'h40+i],resultMem[i]);
            error = error + 1;
        end
    end
    if(error == 0) begin
        $display("****************************************************************");
        $display("***************sucessfull !!!!!!!*******************************");
        $display("****************************************************************");

    end
    else begin
        $display("****************************************************************");
        $display("********************Fail  !!!!!!!*******************************");
        $display("****************************************************************");
    end
    $finish;
end


initial begin
    clk = 1'd1;
    rst = 1'd0;
    #(`CYCLE) rst = 1'd1;
    #(`CYCLE+1) rst = 1'd0;
    #(`CYCLE);
end



endmodule

sim/test.vcd
$date
	Thu Sep 23 22:46:06 2021
$end
$version
	Icarus Verilog
$end
$timescale
	1s
$end
$scope module test $end
$var reg 1 ! clk $end
$var reg 1 " rst $end
$var integer 32 # error [31:0] $end
$var integer 32 $ fd [31:0] $end
$var integer 32 % i [31:0] $end
$var integer 32 & resultLen [31:0] $end
$scope module dut $end
$var wire 1 ! clk $end
$var wire 1 ' instr_mem_read $end
$var wire 1 " rst $end
$var wire 32 ( instr_mem_data_r [31:0] $end
$var wire 32 ) instr_mem_addr [31:0] $end
$var wire 4 * data_mem_write [3:0] $end
$var wire 1 + data_mem_read $end
$var wire 32 , data_mem_data_w [31:0] $end
$var wire 32 - data_mem_data_r [31:0] $end
$var wire 32 . data_mem_addr [31:0] $end
$scope module DM $end
$var wire 1 ! clk $end
$var wire 4 / write [3:0] $end
$var wire 1 + read $end
$var wire 32 0 addrWords [31:0] $end
$var wire 32 1 addr [31:0] $end
$var wire 32 2 DATA_IN [31:0] $end
$var reg 32 3 DATA_OUT [31:0] $end
$upscope $end
$scope module IM $end
$var wire 32 4 DATA_IN [31:0] $end
$var wire 1 ! clk $end
$var wire 1 ' read $end
$var wire 4 5 write [3:0] $end
$var wire 32 6 addrWords [31:0] $end
$var wire 32 7 addr [31:0] $end
$var reg 32 8 DATA_OUT [31:0] $end
$upscope $end
$scope module riscv $end
$var wire 1 ! clk $end
$var wire 32 9 data_mem_addr [31:0] $end
$var wire 32 : data_mem_data_r [31:0] $end
$var wire 32 ; data_mem_data_w [31:0] $end
$var wire 32 < instr_mem_addr [31:0] $end
$var wire 32 = instr_mem_data_r [31:0] $end
$var wire 1 ' instr_mem_read $end
$var wire 32 > next_pc [31:0] $end
$var wire 1 " rst $end
$var wire 2 ? wbSel [1:0] $end
$var wire 32 @ rs2_data [31:0] $end
$var wire 32 A rs1_data [31:0] $end
$var wire 1 B rd_write $end
$var wire 32 C pc_add_4 [31:0] $end
$var wire 3 D pcSel [2:0] $end
$var wire 32 E pc [31:0] $end
$var wire 4 F data_mem_write [3:0] $end
$var wire 1 + data_mem_read $end
$var wire 32 G alu_rs1 [31:0] $end
$var wire 32 H alu_out [31:0] $end
$var wire 2 I aluSrc2Sel [1:0] $end
$var wire 1 J aluSrc1Sel $end
$var wire 4 K aluSel [3:0] $end
$var wire 20 L U_type_imm [19:0] $end
$var wire 32 M S_type_imm_signed_extend [31:0] $end
$var wire 32 N S_type_imm [31:0] $end
$var wire 32 O I_type_imm_signed_extend [31:0] $end
$var wire 32 P I_type_imm [31:0] $end
$var reg 32 Q alu_rs2 [31:0] $end
$var reg 32 R rd_data [31:0] $end
$scope module PC_inst $end
$var wire 1 ! clk $end
$var wire 32 S next_pc [31:0] $end
$var wire 1 " rst $end
$var reg 32 T pc [31:0] $end
$upscope $end
$scope module alu_inst $end
$var wire 32 U rs1_data [31:0] $end
$var wire 32 V rs1_singed [31:0] $end
$var wire 32 W rs2_data [31:0] $end
$var wire 32 X rs2_singed [31:0] $end
$var wire 4 Y aluSel [3:0] $end
$var reg 32 Z alu_out [31:0] $end
$upscope $end
$scope module control_inst $end
$var wire 3 [ funct3 [2:0] $end
$var wire 7 \ funct7 [6:0] $end
$var wire 1 ' instr_mem_read $end
$var wire 7 ] opcode [6:0] $end
$var reg 4 ^ aluSel [3:0] $end
$var reg 1 J aluSrc1Sel $end
$var reg 2 _ aluSrc2Sel [1:0] $end
$var reg 1 + data_mem_read $end
$var reg 4 ` data_mem_write [3:0] $end
$var reg 3 a pcSel [2:0] $end
$var reg 1 B rd_write $end
$var reg 2 b wbSel [1:0] $end
$upscope $end
$scope module regfile_inst $end
$var wire 1 ! clk $end
$var wire 5 c rd_addr [4:0] $end
$var wire 32 d rd_data [31:0] $end
$var wire 1 B rd_write $end
$var wire 5 e rs1_addr [4:0] $end
$var wire 5 f rs2_addr [4:0] $end
$var wire 1 " rst $end
$var wire 32 g rs2_data [31:0] $end
$var wire 32 h rs1_data [31:0] $end
$var integer 32 i i [31:0] $end
$upscope $end
$upscope $end
$upscope $end
$upscope $end
$enddefinitions $end
#0
$dumpvars
bx i
bx h
bx g
bx f
bx e
bx d
bx c
bx b
bx a
bx `
bx _
bx ^
bx ]
bx \
bx [
bx Z
bx Y
bx X
bx W
bx V
bx U
bx T
bx S
bx R
bx Q
b0xxxxxxxxxxxx P
bx O
b0xxxxxxxxxxxx N
bx M
bx L
bx K
xJ
bx I
bx H
bx G
bx F
bx E
bx D
bx C
xB
bx A
bx @
bx ?
bx >
bx =
bx <
bx ;
bx :
bx 9
bx 8
bx 7
b0xxxxxxxxxxxxxxxxxxxxxxxxxxxxxx 6
b0 5
b0 4
bx 3
bx 2
bx 1
b0xxxxxxxxxxxxxxxxxxxxxxxxxxxxxx 0
bx /
bx .
bx -
bx ,
x+
bx *
bx )
bx (
1'
b100 &
b0 %
b10000000000000000000000000000011 $
b0 #
0"
1!
$end
#5
0!
#10
b0 6
b100 >
b100 S
b100 C
b0 )
b0 7
b0 <
b0 E
b0 T
b100000 i
1!
1"
#15
0!
#20
b100000000 R
b100000000 d
b1000000 0
b100000000 .
b100000000 1
b100000000 9
b100000000 H
b100000000 Z
b100000000 X
b100000000 Q
b100000000 W
b0 V
b0 G
b0 U
1B
b10 K
b10 Y
b10 ^
b0 D
b0 a
b0 ?
b0 b
b0 *
b0 /
b0 F
b0 `
0+
b10 I
b10 _
0J
b0 A
b0 h
b0 ,
b0 2
b0 ;
b0 @
b0 g
b100000000 P
b100001000 N
b100001000 M
b100000000 O
b10000000000000000 L
b10011 ]
b0 [
b1000 \
b0 e
b0 f
b1000 c
b10000000000000000010000010011 (
b10000000000000000010000010011 8
b10000000000000000010000010011 =
b100000 i
1!
#21
0"
#25
0!
#30
b1 6
b1000 >
b1000 S
b1000 C
b100 )
b100 7
b100 <
b100 E
b100 T
1!
#35
0!
#40
b10000111011001010100000000000000 R
b10000111011001010100000000000000 d
b100001110110010101000000000000 0
b10000111011001010100000000000000 V
b10000111011001010100000000000000 G
b10000111011001010100000000000000 U
b10000111011001010100000000000000 .
b10000111011001010100000000000000 1
b10000111011001010100000000000000 9
b10000111011001010100000000000000 H
b10000111011001010100000000000000 Z
b0 X
b0 Q
b0 W
b1110 K
b1110 Y
b1110 ^
b0 I
b0 _
1J
b100001110110 P
b100001100101 N
b11111111111111111111100001100101 M
b11111111111111111111100001110110 O
b10000111011001010100 L
b110111 ]
b100 [
b1000011 \
b1010 e
b10110 f
b101 c
b10 6
b10000111011001010100001010110111 (
b10000111011001010100001010110111 8
b10000111011001010100001010110111 =
b1100 >
b1100 S
b1100 C
b1000 )
b1000 7
b1000 <
b1000 E
b1000 T
1!
#45
0!
#50
b10000111011001010100001100100001 R
b10000111011001010100001100100001 d
b100001110110010101000011001000 0
b10000111011001010100001100100001 .
b10000111011001010100001100100001 1
b10000111011001010100001100100001 9
b10000111011001010100001100100001 H
b10000111011001010100001100100001 Z
b1100100001 X
b1100100001 Q
b1100100001 W
b10000111011001010100000000000000 V
b10000111011001010100000000000000 G
b10000111011001010100000000000000 U
b10 K
b10 Y
b10 ^
b10 I
b10 _
0J
b10000111011001010100000000000000 A
b10000111011001010100000000000000 h
b1100100001 P
b1100100101 N
b1100100101 M
b1100100001 O
b110010000100101000 L
b10011 ]
b0 [
b11001 \
b101 e
b1 f
b11 6
b110010000100101000001010010011 (
b110010000100101000001010010011 8
b110010000100101000001010010011 =
b10000 >
b10000 S
b10000 C
b1100 )
b1100 7
b1100 <
b1100 E
b1100 T
1!
#55
0!
#60
b100 R
b100 d
b1 0
b100 .
b100 1
b100 9
b100 H
b100 Z
b100 X
b100 Q
b100 W
b0 V
b0 G
b0 U
b100 P
b110 N
b110 M
b100 O
b10000000000 L
b0 \
b0 e
b100 f
b110 c
b100 6
b0 A
b0 h
b10000000000001100010011 (
b10000000000001100010011 8
b10000000000001100010011 =
b10100 >
b10100 S
b10100 C
b10000 )
b10000 7
b10000 <
b10000 E
b10000 T
1!
#65
0!
#70
b1000011101100101010000110010 R
b1000011101100101010000110010 d
b10000111011001010100001100 0
b1000011101100101010000110010 .
b1000011101100101010000110010 1
b1000011101100101010000110010 9
b1000011101100101010000110010 H
b1000011101100101010000110010 Z
b10000111011001010100001100100001 V
b10000111011001010100001100100001 G
b10000111011001010100001100100001 U
b1001 K
b1001 Y
b1001 ^
b0 I
b0 _
b10000111011001010100001100100001 A
b10000111011001010100001100100001 h
b100 ,
b100 2
b100 ;
b100 @
b100 g
b10000000110 P
b10000000101 N
b10000000101 M
b10000000110 O
b1000000011000101101 L
b110011 ]
b101 [
b100000 \
b101 e
b110 f
b101 c
b101 6
b1000000011000101101001010110011 (
b1000000011000101101001010110011 8
b1000000011000101101001010110011 =
b11000 >
b11000 S
b11000 C
b10100 )
b10100 7
b10100 <
b10100 E
b10100 T
1!
#75
0!
#80
b100001110110010101000011 R
b100001110110010101000011 d
b1000011101100101010000 0
b100001110110010101000011 .
b100001110110010101000011 1
b100001110110010101000011 9
b100001110110010101000011 H
b100001110110010101000011 Z
b1000011101100101010000110010 V
b1000011101100101010000110010 G
b1000011101100101010000110010 U
b110 6
b1000011101100101010000110010 A
b1000011101100101010000110010 h
b11100 >
b11100 S
b11100 C
b11000 )
b11000 7
b11000 <
b11000 E
b11000 T
1!
#85
0!
#90
b10000111011001010100 R
b10000111011001010100 d
b100001110110010101 0
b10000111011001010100 .
b10000111011001010100 1
b10000111011001010100 9
b10000111011001010100 H
b10000111011001010100 Z
b100001110110010101000011 V
b100001110110010101000011 G
b100001110110010101000011 U
b100001110110010101000011 A
b100001110110010101000011 h
b111 6
b100000 >
b100000 S
b100000 C
b11100 )
b11100 7
b11100 <
b11100 E
b11100 T
1!
#95
0!
#100
b1000011101100101 R
b1000011101100101 d
b10000111011001 0
b1000011101100101 .
b1000011101100101 1
b1000011101100101 9
b1000011101100101 H
b1000011101100101 Z
b10000111011001010100 V
b10000111011001010100 G
b10000111011001010100 U
b1000 6
b10000111011001010100 A
b10000111011001010100 h
b100100 >
b100100 S
b100100 C
b100000 )
b100000 7
b100000 <
b100000 E
b100000 T
1!
#105
0!
#110
b100001110110 R
b100001110110 d
b1000011101 0
b100001110110 .
b100001110110 1
b100001110110 9
b100001110110 H
b100001110110 Z
b1000011101100101 V
b1000011101100101 G
b1000011101100101 U
b1000011101100101 A
b1000011101100101 h
b1001 6
b101000 >
b101000 S
b101000 C
b100100 )
b100100 7
b100100 <
b100100 E
b100100 T
1!
#115
0!
#120
b1110111011101110111000000000000 R
b1110111011101110111000000000000 d
b11101110111011101110000000000 0
b1110111011101110111000000000000 .
b1110111011101110111000000000000 1
b1110111011101110111000000000000 9
b1110111011101110111000000000000 H
b1110111011101110111000000000000 Z
b0 X
b0 Q
b0 W
b1110 K
b1110 Y
b1110 ^
1J
b0 ,
b0 2
b0 ;
b0 @
b0 g
b1110111011101110111000000000000 V
b1110111011101110111000000000000 G
b1110111011101110111000000000000 U
b11101110111 P
b11101100110 N
b11101100110 M
b11101110111 O
b1110111011101110111 L
b110111 ]
b111 [
b111011 \
b1110 e
b10111 f
b110 c
b1010 6
b0 A
b0 h
b1110111011101110111001100110111 (
b1110111011101110111001100110111 8
b1110111011101110111001100110111 =
b101100 >
b101100 S
b101100 C
b101000 )
b101000 7
b101000 <
b101000 E
b101000 T
1!
#125
0!
#130
b1110111011101110111011101110111 R
b1110111011101110111011101110111 d
b11101110111011101110111011101 0
b1110111011101110111011101110111 .
b1110111011101110111011101110111 1
b1110111011101110111011101110111 9
b1110111011101110111011101110111 H
b1110111011101110111011101110111 Z
b11101110111 X
b11101110111 Q
b11101110111 W
b1110111011101110111000000000000 V
b1110111011101110111000000000000 G
b1110111011101110111000000000000 U
b10 K
b10 Y
b10 ^
b10 I
b10 _
0J
b1110111011101110111000000000000 A
b1110111011101110111000000000000 h
b1110111011100110000 L
b10011 ]
b0 [
b110 e
b1011 6
b1110111011100110000001100010011 (
b1110111011100110000001100010011 8
b1110111011100110000001100010011 =
b110000 >
b110000 S
b110000 C
b101100 )
b101100 7
b101100 <
b101100 E
b101100 T
1!
#135
0!
#140
b111011101 R
b111011101 d
b1110111 0
b111011101 .
b111011101 1
b111011101 9
b111011101 H
b111011101 Z
b100001110110 X
b100001110110 Q
b100001110110 W
b1001 K
b1001 Y
b1001 ^
b0 I
b0 _
b100001110110 ,
b100001110110 2
b100001110110 ;
b100001110110 @
b100001110110 g
b1110111011101110111011101110111 V
b1110111011101110111011101110111 G
b1110111011101110111011101110111 U
b10000000101 P
b10000000101 N
b10000000101 M
b10000000101 O
b1000000010100110101 L
b110011 ]
b101 [
b100000 \
b101 f
b101 c
b1100 6
b1110111011101110111011101110111 A
b1110111011101110111011101110111 h
b1000000010100110101001010110011 (
b1000000010100110101001010110011 8
b1000000010100110101001010110011 =
b110100 >
b110100 S
b110100 C
b110000 )
b110000 7
b110000 <
b110000 E
b110000 T
1!
#145
0!
#150
b11 R
b11 d
b0 0
b11 .
b11 1
b11 9
b11 H
b11 Z
b111011101 X
b111011101 Q
b111011101 W
b111011101 ,
b111011101 2
b111011101 ;
b111011101 @
b111011101 g
b1101 6
b111000 >
b111000 S
b111000 C
b110100 )
b110100 7
b110100 <
b110100 E
b110100 T
1!
#155
0!
#160
b1110111011101110111011101110 R
b1110111011101110111011101110 d
b11101110111011101110111011 0
b1110111011101110111011101110 .
b1110111011101110111011101110 1
b1110111011101110111011101110 9
b1110111011101110111011101110 H
b1110111011101110111011101110 Z
b11 X
b11 Q
b11 W
b1110 6
b11 ,
b11 2
b11 ;
b11 @
b11 g
b111100 >
b111100 S
b111100 C
b111000 )
b111000 7
b111000 <
b111000 E
b111000 T
1!
#165
0!
#170
b11101110111011101 R
b11101110111011101 d
b111011101110111 0
b11101110111011101 .
b11101110111011101 1
b11101110111011101 9
b11101110111011101 H
b11101110111011101 Z
b1110111011101110111011101110 X
b1110111011101110111011101110 Q
b1110111011101110111011101110 W
b1110111011101110111011101110 ,
b1110111011101110111011101110 2
b1110111011101110111011101110 ;
b1110111011101110111011101110 @
b1110111011101110111011101110 g
b1111 6
b1000000 >
b1000000 S
b1000000 C
b111100 )
b111100 7
b111100 <
b111100 E
b111100 T
1!
#175
0!
#180
b11 R
b11 d
b0 0
b11 .
b11 1
b11 9
b11 H
b11 Z
b11101110111011101 X
b11101110111011101 Q
b11101110111011101 W
b10000 6
b11101110111011101 ,
b11101110111011101 2
b11101110111011101 ;
b11101110111011101 @
b11101110111011101 g
b1000100 >
b1000100 S
b1000100 C
b1000000 )
b1000000 7
b1000000 <
b1000000 E
b1000000 T
1!
#185
0!
#190
b1000000 0
bx R
bx d
b100000000 V
b100000000 G
b100000000 U
b100000000 .
b100000000 1
b100000000 9
b100000000 H
b100000000 Z
0B
b10 K
b10 Y
b10 ^
b1 ?
b1 b
b1111 *
b1111 /
b1111 F
b1111 `
b1 I
b1 _
b100000000 A
b100000000 h
b0 X
b0 Q
b0 W
b101 P
b0 N
b0 M
b101 O
b10101000010 L
b100011 ]
b10 [
b0 \
b1000 e
b0 c
b11 ,
b11 2
b11 ;
b11 @
b11 g
b10001 6
b10101000010000000100011 (
b10101000010000000100011 8
b10101000010000000100011 =
b1001000 >
b1001000 S
b1001000 C
b1000100 )
b1000100 7
b1000100 <
b1000100 E
b1000100 T
1!
#195
0!
#200
b1000001 0
b100000100 .
b100000100 1
b100000100 9
b100000100 H
b100000100 Z
b100 X
b100 Q
b100 W
b0 ,
b0 2
b0 ;
b0 @
b0 g
b0 P
b100 N
b100 M
b0 O
b1000010 L
b0 f
b100 c
b10010 6
b1000010001000100011 (
b1000010001000100011 8
b1000010001000100011 =
b1001100 >
b1001100 S
b1001100 C
b1001000 )
b1001000 7
b1001000 <
b1001000 E
b1001000 T
1!
#205
0!
#210
b1000010 0
b100001000 .
b100001000 1
b100001000 9
b100001000 H
b100001000 Z
b1000 X
b1000 Q
b1000 W
b1000 N
b1000 M
b1000 c
b10011 6
b1000010010000100011 (
b1000010010000100011 8
b1000010010000100011 =
b1010000 >
b1010000 S
b1010000 C
b1001100 )
b1001100 7
b1001100 <
b1001100 E
b1001100 T
1!
#215
0!
#220
b1000011 0
b100001100 .
b100001100 1
b100001100 9
b100001100 H
b100001100 Z
b1100 X
b1100 Q
b1100 W
b1100 N
b1100 M
b1100 c
b10100 6
b1000010011000100011 (
b1000010011000100011 8
b1000010011000100011 =
b1010100 >
b1010100 S
b1010100 C
b1010000 )
b1010000 7
b1010000 <
b1010000 E
b1010000 T
1!
#225
0!
#230
b10000000 0
b1000000000 .
b1000000000 1
b1000000000 9
b1000000000 H
b1000000000 Z
b1000000000 R
b1000000000 d
b0 V
b0 G
b0 U
b1000000000 X
b1000000000 Q
b1000000000 W
1B
b0 ?
b0 b
b0 *
b0 /
b0 F
b0 `
b10 I
b10 _
b0 A
b0 h
b1000000000 P
b1000001000 N
b1000001000 M
b1000000000 O
b100000000000000000 L
b10011 ]
b0 [
b10000 \
b0 e
b1000 c
b10101 6
b100000000000000000010000010011 (
b100000000000000000010000010011 8
b100000000000000000010000010011 =
b1011000 >
b1011000 S
b1011000 C
b1010100 )
b1010100 7
b1010100 <
b1010100 E
b1010100 T
1!
#235
0!
