rtl/ram.v
module ram #(parameter words = 65536)
(
    input clk,
    input [31:0] addr,
    input read,
    input [3:0] write,
    input [31:0] DATA_IN,
    output reg [31:0] DATA_OUT
);
reg [31:0] mem [0:words-1];
wire [31:0] addrWords = {2'd0,addr[31:2]};

always@(*) begin
    DATA_OUT = mem[addrWords];
end
/*
always @(posedge clk) begin
    if(read) DATA_OUT <= mem[addrWords];
end
*/
always @(posedge clk) begin
    if(write[0]) mem[addrWords][7:0] <= DATA_IN[7:0];
    if(write[1]) mem[addrWords][15:8] <= DATA_IN[15:8];
    if(write[2]) mem[addrWords][23:16] <= DATA_IN[23:16];
    if(write[3]) mem[addrWords][31:24] <= DATA_IN[31:24];
end

endmodule

rtl/refer/CPU.sv
// Please include verilog file if you write module in other file
module CPU(
    input             clk,
    input             rst,
    input      [31:0] data_out,
    input      [31:0] instr_out,
    output            instr_read,
    output            data_read,
    output     [31:0] instr_addr,
    output     [31:0] data_addr,
    output reg [3:0]  data_write,
    output reg [31:0] data_in
);

/* Add your design */

// PC related
reg [31:0] pc_in;
wire [31:0] pc_out;
assign instr_read = 1'b1; // always read the instruction
assign instr_addr = pc_out;
PC PC(
	.clk(clk),
	.rst(rst),
	.pc_in(pc_in),
	.pc_out(pc_out)
);

// Decoder related
wire [2:0] ImmType;
wire RegWrite/*, isBranch*/, PCtoRegSrc, ALUSrc, RDSrc/*, MemRead*/, MemWrite, MemtoReg;
wire [1:0] isBranch;
wire [2:0] ALUOP;
Decoder Decoder(
	.opcode(instr_out[6:0]),
	.Funct3(instr_out[14:12]),
	.ImmType(ImmType),
	.RegWrite(RegWrite),
	.isBranch(isBranch),
	.PCtoRegSrc(PCtoRegSrc),
	.ALUSrc(ALUSrc),
	.RDSrc(RDSrc),
	.MemRead(data_read), // (MemRead),
	.MemWrite(MemWrite), // (MemWrite), 
	.MemtoReg(MemtoReg),
	.ALUOP(ALUOP)
);

// ImmGen related
wire [31:0] Imm;
ImmGen ImmGen(
	.instr_out(instr_out),
	.ImmType(ImmType),
	.Imm(Imm)
);

//ALUCtrl related
wire [3:0] ALUCtrl;
ALUCtrl ALUControl(
	.ALUOP(ALUOP),
	.Funct7(instr_out[31:25]),
	.Funct3(instr_out[14:12]),
	.ALUCtrl(ALUCtrl)
);

// Register related
wire [31:0] rs1_data;
wire [31:0] rs2_data;
wire [31:0] rd_data;
Register Register(
	.clk(clk),
	.rst(rst),
	.rs1_addr(instr_out[19:15]),
	.rs2_addr(instr_out[24:20]),
	.rd_addr(instr_out[11:7]),
	.rd_data(rd_data), //need to fix, wire WB
	.RegWrite(RegWrite),
	.rs1_data(rs1_data),
	.rs2_data(rs2_data)
);

// mux and wire before ALU
wire [31:0] pc4;
assign pc4 = pc_out + 31'b100;

wire [31:0] pcimm;
assign pcimm = pc_out + Imm;

wire [31:0] pc_to_reg;
assign pc_to_reg = PCtoRegSrc? pcimm:pc4;

wire [31:0] rs2_data_alu; // final rs2_data
assign rs2_data_alu = ALUSrc? rs2_data:Imm;

// ALU related
wire ZeroFlag;
wire [31:0] alu_out;
ALU ALU(
	.rs1_data(rs1_data),
	.rs2_data(rs2_data_alu),
	.ALUCtrl(ALUCtrl),
	.ZeroFlag(ZeroFlag),
	.alu_out(alu_out)
);

// mux and wire after ALU
wire [31:0] pc_or_alu_out;
assign pc_or_alu_out = RDSrc? pc_to_reg:alu_out;

//DM related
assign data_addr = alu_out;
//assign data_in = rs2_data;

//Awesome
/*From JiaWei start*/
always@(*) begin
    data_write = 4'b0;
    if(MemWrite)begin
        case(instr_out[14:12]) // Funct3   
        	// byte
            3'b000:data_write[data_addr[1:0]]=1'b1;
            // half
            3'b001:data_write[{data_addr[1],1'b0}+:2] = 2'b11;
            //word
            default:data_write = 4'b1111; 
        endcase 
    end
end

always@(*) begin
    data_in = 32'b0;
    case(instr_out[14:12]) // Funct3
    		// byte
            3'b000:data_in[{data_addr[1:0],3'b0}+:8] = rs2_data[7:0];
            // half
            3'b001:data_in[{data_addr[1],4'b0}+:16]= rs2_data[15:0];
            // word
            default:data_in = rs2_data; 
    endcase
end
/*From JiaWei end*/

reg [31:0] mem_out;

always@(*) begin
	case(instr_out[14:12]) // Funct3
		// bs
		3'b000: mem_out = {{24{data_out[7]}}, data_out[7:0]};
		// hs
		3'b001: mem_out = {{16{data_out[15]}}, data_out[15:0]};
		// bu
		3'b100: mem_out = {24'b0, data_out[7:0]};
		// hu
		3'b101: mem_out = {16'b0, data_out[15:0]};
		// word
		default: mem_out = data_out;
	endcase
end

// write back rigester
assign rd_data = MemtoReg? mem_out:pc_or_alu_out;

//BranchCtrl
// 00 PC+4
// 01 PCIMM
// 10 alu_out
wire [1:0] BranchCtrl;
BranchCtrl BranchControl(
	.isBranch(isBranch),
	.ZeroFlag(ZeroFlag),
	.alu_out(alu_out),
	.Funct3(instr_out[14:12]),
	.BranchCtrl(BranchCtrl)
);

//pc_in
always@(*) begin
	case(BranchCtrl)
		2'b00: pc_in = pc4;
		2'b01: pc_in = pcimm;
		2'b10: pc_in = alu_out;
		default: pc_in = pc4;
	endcase
end
endmodule
/*---------------------------------------------------------------------------------------------------------*/
/*------PC begin------*/
module PC(clk, rst, pc_in, pc_out);
input clk, rst;
input [31:0] pc_in;
output reg [31:0] pc_out;

reg [1:0] enWrite;

always @(posedge clk or posedge rst) begin
	if (rst) begin
		pc_out <= 32'b0;
	end
	else begin
		if(enWrite == 2'b10)
			pc_out <= pc_in;
	end
end

always @(posedge clk or posedge rst) begin
	if (rst) begin
		enWrite <= 2'b0;
	end
	else begin
		case(enWrite)
			2'b10: enWrite <= 2'b0;
			default: enWrite <= enWrite + 2'b1;
		endcase
	end
end
endmodule
/*------PC end------*/

/*------Decoder begin------*/
module Decoder(opcode, Funct3, ImmType, RegWrite, isBranch, PCtoRegSrc, ALUSrc, RDSrc, MemRead, MemWrite, MemtoReg, ALUOP);
input [6:0] opcode;
input [2:0] Funct3;
output reg [2:0] ImmType;
// 000 R-type
// 001 I-type
// 010 S-type
// 011 B-type
// 100 U-type
// 101 J-type

output reg RegWrite/*, isBranch*/, PCtoRegSrc, ALUSrc, RDSrc, MemRead, MemWrite, MemtoReg;
output reg [1:0] isBranch;
// 00 NONE
// 01 JALR
// 10 B-type
// 11 JAL
output reg [2:0] ALUOP;
// 000 R-type
// 001 I-type
// 010 add
// 011 sub
// 100 U-type

always@(*) begin
	case(opcode)
		7'b0110011: begin // R-type
			ImmType		= 3'b000;
			RegWrite 	= 1'b1;
			isBranch 	= 2'b00;
			PCtoRegSrc 	= 1'b0; // need to check
			ALUSrc		= 1'b1;
			RDSrc 		= 1'b0; // need to check
			MemRead 	= 1'b0;
			MemWrite 	= 1'b0;
			MemtoReg 	= 1'b0;
			ALUOP		= 3'b000;
		end
		7'b0000011: begin // I-type
			ImmType		= 3'b001;
			RegWrite 	= 1'b1;
			isBranch 	= 2'b00;
			PCtoRegSrc 	= 1'b0; // need to check
			ALUSrc		= 1'b0;
			RDSrc 		= 1'b0; // need to check
			MemRead 	= 1'b1;
			MemWrite 	= 1'b0;
			MemtoReg 	= 1'b1;
			ALUOP		= 3'b010;
		end
		7'b0010011: begin // I-type
			ImmType		= 3'b001;
			RegWrite 	= 1'b1;
			isBranch 	= 2'b00;
			PCtoRegSrc 	= 1'b0; // need to check
			ALUSrc		= 1'b0;
			RDSrc 		= 1'b0;
			MemRead 	= 1'b0;
			MemWrite 	= 1'b0;
			MemtoReg 	= 1'b0;
			ALUOP		= 3'b001;
		end
		7'b1100111: begin // I-type
			ImmType		= 3'b001;
			RegWrite 	= 1'b1;
			isBranch 	= 2'b01; // need to fix
			PCtoRegSrc 	= 1'b0; // rd = PC + 4
			ALUSrc		= 1'b0;
			RDSrc 		= 1'b1; // rd = PC + 4
			MemRead 	= 1'b0;
			MemWrite 	= 1'b0;
			MemtoReg 	= 1'b0;
			ALUOP		= 3'b010;
		end
		7'b0100011: begin // S-type
			ImmType		= 3'b010;
			RegWrite 	= 1'b0;
			isBranch 	= 2'b00;
			PCtoRegSrc 	= 1'b0;
			ALUSrc		= 1'b0;
			RDSrc 		= 1'b0;
			MemRead 	= 1'b0;
			MemWrite 	= 1'b1;
			MemtoReg 	= 1'b0;
			ALUOP		= 3'b010;
			// case(Funct3)
			// 	3'b000: MemWrite = 4'b0001; // BYTE
			// 	3'b001: MemWrite = 4'b0011; // HALF
			// 	default: MemWrite = 4'b1111; // WORD
			// endcase
		end
		7'b1100011: begin // B-type
			ImmType		= 3'b011;
			RegWrite 	= 1'b0;
			isBranch 	= 2'b10; // need to fix
			PCtoRegSrc 	= 1'b1;
			ALUSrc		= 1'b1;
			RDSrc 		= 1'b0;
			MemRead 	= 1'b0;
			MemWrite 	= 1'b0;
			MemtoReg 	= 1'b0;
			ALUOP		= 3'b011;
		end
		7'b0010111: begin // U-type
			ImmType		= 3'b100;
			RegWrite 	= 1'b1;
			isBranch 	= 2'b00;
			PCtoRegSrc 	= 1'b1;
			ALUSrc		= 1'b0;
			RDSrc 		= 1'b1;
			MemRead 	= 1'b0;
			MemWrite 	= 1'b0;
			MemtoReg 	= 1'b0;
			ALUOP		= 3'b010;
		end
		7'b0110111: begin // U-type
			ImmType		= 3'b100;
			RegWrite 	= 1'b1;
			isBranch 	= 2'b00;
			PCtoRegSrc 	= 1'b1;
			ALUSrc		= 1'b0;
			RDSrc 		= 1'b0;
			MemRead 	= 1'b0;
			MemWrite 	= 1'b0;
			MemtoReg 	= 1'b0;
			ALUOP		= 3'b100; // need to fix, rd = imm
		end
		7'b1101111: begin // J-type
			ImmType		= 3'b101;
			RegWrite 	= 1'b1;
			isBranch 	= 2'b11; // need to fix
			PCtoRegSrc 	= 1'b0; // rd = PC + 4
			ALUSrc		= 1'b0;
			RDSrc 		= 1'b1;
			MemRead 	= 1'b0;
			MemWrite 	= 1'b0;
			MemtoReg 	= 1'b0;
			ALUOP		= 3'b010;
		end
	endcase
end
endmodule
/*------Decoder end------*/

/*------ImmGen start------*/
// 000 R-type
// 001 I-type
// 010 S-type
// 011 B-type
// 100 U-type
// 101 J-type

module ImmGen(instr_out, ImmType, Imm);
input  [31:0] 	instr_out;
input  [2:0]	ImmType;
output reg [31:0]	Imm;

always @(*) begin
	case(ImmType)
		3'b001: begin // I-type
			if((instr_out[6:0] == 7'b0010011) && instr_out[14:12] == 3'b101 && instr_out[31:25] == 7'b0100000)
				Imm = {27'b0, instr_out[24:20]};
			else
				Imm = {{20{instr_out[31]}}, instr_out[31:20]};
		end
		3'b010: begin // S-type
			Imm = {{20{instr_out[31]}}, instr_out[31:25], instr_out[11:7]};
		end
		3'b011: begin // B-type
			Imm = {{19{instr_out[31]}}, instr_out[31], instr_out[7], instr_out[30:25], instr_out[11:8], 1'b0};
		end
		3'b100: begin // U-type
			Imm = {instr_out[31:12], 12'b0};
		end
		3'b101: begin
			Imm = {{11{instr_out[31]}}, instr_out[31], instr_out[19:12], instr_out[20], instr_out[30:21], 1'b0};
		end
		default: begin
			Imm = 32'b0;
		end
	endcase
end
endmodule
/*------ImmGen end------*/

/*------ALUCtrl start------*/
// 000 R-type
// 001 I-type
// 010 add
// 011 sub
// 100 U-type
module ALUCtrl(ALUOP, Funct7, Funct3, ALUCtrl);
input [2:0] ALUOP;
input [6:0] Funct7;
input [2:0] Funct3;
output reg [3:0] ALUCtrl;

parameter [3:0] ADD 	= 4'b0000,
				SUB 	= 4'b0001,
				SLL 	= 4'b0010,
				SLT 	= 4'b0011,
				SLTU 	= 4'b0100,
				XOR 	= 4'b0101,
				SRL 	= 4'b0110,
				SRA 	= 4'b0111,
				OR 		= 4'b1000,
				AND 	= 4'b1001,
				MUL 	= 4'b1010,
				MULH 	= 4'b1011,
				MULHU 	= 4'b1100,
				IMM 	= 4'b1101; // for "rd = imm"

always @(*) begin
	// MemWidth = WORD;
	case(ALUOP)
		3'b000: begin // R-type
			case(Funct3)
				3'b000: begin // ALUCtrl = (Funct7 == 7'b0000000)? ADD:SUB;
					case(Funct7)
						7'b0100000: ALUCtrl = SUB;
						7'b0000001: ALUCtrl = MUL;
						default: 	ALUCtrl = ADD;
					endcase
				end
				3'b001: ALUCtrl = (Funct7 == 7'b0000000)? SLL:MULH;
				3'b010: ALUCtrl = SLT;
				3'b011: ALUCtrl = (Funct7 == 7'b0000000)? SLTU:MULHU;
				3'b100: ALUCtrl = XOR;
				3'b101: ALUCtrl = (Funct7 == 7'b0000000)? SRL:SRA;
				3'b110: ALUCtrl = OR;
				3'b111: ALUCtrl = AND;
			endcase
		end
		3'b001: begin // I-type except LW
			case(Funct3)
				3'b000: ALUCtrl = ADD;
				3'b010: ALUCtrl = SLT;
				3'b011: ALUCtrl = SLTU;
				3'b100: ALUCtrl = XOR;
				3'b110: ALUCtrl = OR;
				3'b111: ALUCtrl = AND;
				3'b001: ALUCtrl = SLL;
				3'b101: ALUCtrl = (Funct7 == 7'b0000000)? SRL:SRA;
			endcase
		end
		3'b010: begin // LW
			ALUCtrl = ADD;
		end
		3'b011: begin // B-type
			case(Funct3)
				3'b000: ALUCtrl = SUB; // rs1 == rs2
				3'b001:	ALUCtrl = SUB; // rs1 != rs2
				3'b100: ALUCtrl = SLT;
				3'b101: ALUCtrl = SLT;
				3'b110: ALUCtrl = SLTU;
				3'b111: ALUCtrl = SLTU;
				default: ALUCtrl = SUB;
			endcase
		end
		3'b100: begin // U-type
			ALUCtrl = IMM;
		end
		default: begin // unused
			ALUCtrl = ADD;
		end
	endcase
end
endmodule
/*------ALUCtrl end------*/

/*------RegisterFile start------*/
module Register(clk, rst, rs1_addr, rs2_addr, rd_addr, rd_data, RegWrite, rs1_data, rs2_data);
input clk, rst;
input [4:0] rs1_addr, rs2_addr, rd_addr;
input [31:0] rd_data;
input RegWrite;
output [31:0] rs1_data, rs2_data;

reg [31:0] register [31:0];
reg [2:0] enWrite; // for each instr 2 cycles

assign rs1_data = register[rs1_addr];
assign rs2_data = register[rs2_addr];

integer i;
always@(posedge clk or posedge rst) begin
	if(rst) begin
		for(i = 0; i < 32; i = i + 1)
			register[i] <= 32'b0;
	end
	else begin
		if(RegWrite && (enWrite == 2'b10))
			register[rd_addr] <= (rd_addr == 0)? 32'b0:rd_data; // need to fix 0 register
	end
end

always @(posedge clk or posedge rst) begin
	if (rst) begin
		enWrite <= 2'b0;
	end
	else begin
		case(enWrite)
			2'b10: enWrite <= 2'b0;
			default: enWrite <= enWrite + 2'b1;
		endcase
	end
end
endmodule
/*------RegisterFile end------*/

/*------ALU start------*/
module ALU(rs1_data, rs2_data, ALUCtrl, ZeroFlag, alu_out);
input [31:0] rs1_data, rs2_data;
input [3:0] ALUCtrl;
output ZeroFlag;
output reg [31:0] alu_out;

wire signed [31:0] signed_rs1_data, signed_rs2_data;
assign signed_rs1_data = rs1_data;
assign signed_rs2_data = rs2_data;

wire [63:0] mul_result, signed_mul_result;
assign mul_result = rs1_data * rs2_data;
assign signed_mul_result = signed_rs1_data * signed_rs2_data;

assign ZeroFlag = ~|alu_out; 

parameter [3:0] ADD 	= 4'b0000,
				SUB 	= 4'b0001,
				SLL 	= 4'b0010,
				SLT 	= 4'b0011,
				SLTU 	= 4'b0100,
				XOR 	= 4'b0101,
				SRL 	= 4'b0110,
				SRA 	= 4'b0111,
				OR 		= 4'b1000,
				AND 	= 4'b1001,
				MUL 	= 4'b1010,
				MULH 	= 4'b1011,
				MULHU 	= 4'b1100,
				IMM 	= 4'b1101; // for "rd = imm"

always@(*) begin
	case(ALUCtrl)
		ADD: 	alu_out = rs1_data + rs2_data;
		SUB: 	alu_out = rs1_data - rs2_data;
		SLL: 	alu_out = rs1_data << rs2_data[4:0];
		SLT: 	alu_out = (signed_rs1_data < signed_rs2_data)? 32'b1:32'b0;
		SLTU: 	alu_out = (rs1_data < rs2_data)? 32'b1:32'b0;
		XOR: 	alu_out = rs1_data ^ rs2_data;
		SRL: 	alu_out = rs1_data >> rs2_data[4:0];
		SRA: 	alu_out = signed_rs1_data >>> rs2_data[4:0];
		OR: 	alu_out = rs1_data | rs2_data;
		AND: 	alu_out = rs1_data & rs2_data;
		MUL: 	alu_out = signed_mul_result[31:0];
		MULH: 	alu_out = signed_mul_result[63:32];
		MULHU: 	alu_out = mul_result[63:32];
		IMM: 	alu_out = rs2_data;
	endcase
end
endmodule
/*------ALU end------*/

/*------BranchCtrl start------*/
module BranchCtrl(isBranch, ZeroFlag, alu_out, Funct3, BranchCtrl);
input [1:0] isBranch;
// 00 NONE
// 01 JALR
// 10 B-type
// 11 JAL
input ZeroFlag;
input [31:0] alu_out;
input [2:0] Funct3;

output reg [1:0] BranchCtrl;
// 00 PC+4
// 01 PCIMM
// 10 alu_out
parameter [1:0] PC4    = 2'b00,
				PCIMM  = 2'b01,
				ALUOUT = 2'b10;

always@(*) begin
	case(isBranch)
		2'b01: BranchCtrl = ALUOUT;
		2'b10: begin
			case(Funct3)
				3'b000: BranchCtrl = ZeroFlag? PCIMM:PC4;
				3'b001: BranchCtrl = (~ZeroFlag)? PCIMM:PC4;
				3'b100: BranchCtrl = (|alu_out)? PCIMM:PC4;
				3'b101: BranchCtrl = (~|alu_out)? PCIMM:PC4;
				3'b110: BranchCtrl = (|alu_out)? PCIMM:PC4;
				3'b111: BranchCtrl = (~|alu_out)? PCIMM:PC4;
			endcase
		end
		2'b11: BranchCtrl = PCIMM;
		default: BranchCtrl = PC4;
	endcase
end
endmodule
/*------BranchCtrl end------*/

rtl/top.sv
module top #(parameter memWords = 100)
(
    input clk, 
    input rst
);

wire        instr_read;
wire [31:0] instr_addr;
wire [31:0] instr_out;
wire        data_read;
wire [3:0]  data_write;
wire [31:0] data_addr;
wire [31:0] data_in;
wire [31:0] data_out;

CPU i_CPU(
    .clk        (clk),
    .rst        (rst),
    .instr_read (instr_read),
    .instr_addr (instr_addr),
    .instr_out  (instr_out),
    .data_read  (data_read),
    .data_write (data_write),
    .data_addr  (data_addr),
    .data_in    (data_in),
    .data_out   (data_out)
);

ram #(.words(memWords))IM(
    .clk        (clk),
    .addr       (instr_addr),
    .read       (instr_read),
    .write      (4'b0),
    .DATA_IN    (32'b0),
    .DATA_OUT   (instr_out)
);
ram #(.words(memWords)) DM(
    .clk        (clk),
    .addr       (data_addr),
    .read       (data_read),
    .write      (data_write),
    .DATA_IN    (data_in),
    .DATA_OUT   (data_out)
);


endmodule

sim/tb.sv
`define CYCLE 10
`define END 1000
//`define instr "add"
`define HexPath {"./asm/",`instr,"/",`instr,".hex"} 
`define SigPath {"./asm/",`instr,"/",`instr,".sig.dat.hex"} 

module test #(parameter Path = "./asm/add/add.hex");

reg clk,rst;
reg [31:0] resultMem [0:255];
top #(.memWords(100)) dut(
    .clk(clk),
    .rst(rst)
);

int fd,resultLen=0,i=0,error=0;
initial begin
    $readmemh(`HexPath,dut.IM.mem);
    $readmemh(`HexPath,dut.DM.mem);
    fd = $fopen(`SigPath,"r");
   // $display("***%s***",`instr);
    do begin
        $fscanf(fd,"%h",resultMem[resultLen]);
        if(!$feof(fd)) resultLen = resultLen +1;
    end while (!$feof(fd));
end

always #(`CYCLE/2) clk = ~clk;

initial begin
    `ifdef iverilog
        $dumpfile("./test.vcd");
        $dumpvars;
    `else
        $fsdbDumpfile("./test.fsdb");
        $fsdbDumpvars;
        $fsdbDumpMDA;
    `endif 
    
    #(`END) 
    for(i=0;i<resultLen;i++) begin
        if(resultMem[i] == dut.DM.mem[32'h40+i]) begin
            $display("correc, %h",resultMem[i]);
        end
        else begin
            $display("error , %d %h != %h (expected)",i,dut.DM.mem[32'h40+i],resultMem[i]);
            error = error + 1;
        end
    end
    if(error == 0) begin
        $display("****************************************************************");
        $display("***************sucessfull !!!!!!!*******************************");
        $display("****************************************************************");

    end
    else begin
        $display("****************************************************************");
        $display("********************Fail  !!!!!!!*******************************");
        $display("****************************************************************");
    end
    $finish;
end


initial begin
    clk = 1'd1;
    rst = 1'd0;
    #(`CYCLE) rst = 1'd1;
    #(`CYCLE+1) rst = 1'd0;
    #(`CYCLE);
end



endmodule

sim/test.vcd
$date
	Tue Aug 31 22:38:59 2021
$end
$version
	Icarus Verilog
$end
$timescale
	1s
$end
$scope module test $end
$var reg 1 ! clk $end
$var reg 1 " rst $end
$var integer 32 # error [31:0] $end
$var integer 32 $ fd [31:0] $end
$var integer 32 % i [31:0] $end
$var integer 32 & resultLen [31:0] $end
$scope module dut $end
$var wire 1 ! clk $end
$var wire 1 ' instr_read $end
$var wire 1 " rst $end
$var wire 32 ( instr_out [31:0] $end
$var wire 32 ) instr_addr [31:0] $end
$var wire 4 * data_write [3:0] $end
$var wire 1 + data_read $end
$var wire 32 , data_out [31:0] $end
$var wire 32 - data_in [31:0] $end
$var wire 32 . data_addr [31:0] $end
$scope module DM $end
$var wire 1 ! clk $end
$var wire 4 / write [3:0] $end
$var wire 1 + read $end
$var wire 32 0 addrWords [31:0] $end
$var wire 32 1 addr [31:0] $end
$var wire 32 2 DATA_IN [31:0] $end
$var reg 32 3 DATA_OUT [31:0] $end
$upscope $end
$scope module IM $end
$var wire 32 4 DATA_IN [31:0] $end
$var wire 1 ! clk $end
$var wire 1 ' read $end
$var wire 4 5 write [3:0] $end
$var wire 32 6 addrWords [31:0] $end
$var wire 32 7 addr [31:0] $end
$var reg 32 8 DATA_OUT [31:0] $end
$upscope $end
$scope module i_CPU $end
$var wire 1 ! clk $end
$var wire 32 9 data_addr [31:0] $end
$var wire 32 : data_out [31:0] $end
$var wire 32 ; instr_addr [31:0] $end
$var wire 32 < instr_out [31:0] $end
$var wire 1 ' instr_read $end
$var wire 1 " rst $end
$var wire 32 = rs2_data_alu [31:0] $end
$var wire 32 > rs2_data [31:0] $end
$var wire 32 ? rs1_data [31:0] $end
$var wire 32 @ rd_data [31:0] $end
$var wire 32 A pcimm [31:0] $end
$var wire 32 B pc_to_reg [31:0] $end
$var wire 32 C pc_out [31:0] $end
$var wire 32 D pc_or_alu_out [31:0] $end
$var wire 32 E pc4 [31:0] $end
$var wire 2 F isBranch [1:0] $end
$var wire 1 + data_read $end
$var wire 32 G alu_out [31:0] $end
$var wire 1 H ZeroFlag $end
$var wire 1 I RegWrite $end
$var wire 1 J RDSrc $end
$var wire 1 K PCtoRegSrc $end
$var wire 1 L MemtoReg $end
$var wire 1 M MemWrite $end
$var wire 3 N ImmType [2:0] $end
$var wire 32 O Imm [31:0] $end
$var wire 2 P BranchCtrl [1:0] $end
$var wire 1 Q ALUSrc $end
$var wire 3 R ALUOP [2:0] $end
$var wire 4 S ALUCtrl [3:0] $end
$var reg 32 T data_in [31:0] $end
$var reg 4 U data_write [3:0] $end
$var reg 32 V mem_out [31:0] $end
$var reg 32 W pc_in [31:0] $end
$scope module ALU $end
$var wire 32 X rs2_data [31:0] $end
$var wire 32 Y signed_rs1_data [31:0] $end
$var wire 32 Z signed_rs2_data [31:0] $end
$var wire 64 [ signed_mul_result [63:0] $end
$var wire 32 \ rs1_data [31:0] $end
$var wire 64 ] mul_result [63:0] $end
$var wire 1 H ZeroFlag $end
$var wire 4 ^ ALUCtrl [3:0] $end
$var reg 32 _ alu_out [31:0] $end
$upscope $end
$scope module ALUControl $end
$var wire 3 ` Funct3 [2:0] $end
$var wire 7 a Funct7 [6:0] $end
$var wire 3 b ALUOP [2:0] $end
$var reg 4 c ALUCtrl [3:0] $end
$upscope $end
$scope module BranchControl $end
$var wire 3 d Funct3 [2:0] $end
$var wire 1 H ZeroFlag $end
$var wire 32 e alu_out [31:0] $end
$var wire 2 f isBranch [1:0] $end
$var reg 2 g BranchCtrl [1:0] $end
$upscope $end
$scope module Decoder $end
$var wire 3 h Funct3 [2:0] $end
$var wire 7 i opcode [6:0] $end
$var reg 3 j ALUOP [2:0] $end
$var reg 1 Q ALUSrc $end
$var reg 3 k ImmType [2:0] $end
$var reg 1 + MemRead $end
$var reg 1 M MemWrite $end
$var reg 1 L MemtoReg $end
$var reg 1 K PCtoRegSrc $end
$var reg 1 J RDSrc $end
$var reg 1 I RegWrite $end
$var reg 2 l isBranch [1:0] $end
$upscope $end
$scope module ImmGen $end
$var wire 3 m ImmType [2:0] $end
$var wire 32 n instr_out [31:0] $end
$var reg 32 o Imm [31:0] $end
$upscope $end
$scope module PC $end
$var wire 1 ! clk $end
$var wire 32 p pc_in [31:0] $end
$var wire 1 " rst $end
$var reg 2 q enWrite [1:0] $end
$var reg 32 r pc_out [31:0] $end
$upscope $end
$scope module Register $end
$var wire 1 I RegWrite $end
$var wire 1 ! clk $end
$var wire 5 s rd_addr [4:0] $end
$var wire 32 t rd_data [31:0] $end
$var wire 5 u rs1_addr [4:0] $end
$var wire 32 v rs1_data [31:0] $end
$var wire 5 w rs2_addr [4:0] $end
$var wire 32 x rs2_data [31:0] $end
$var wire 1 " rst $end
$var reg 3 y enWrite [2:0] $end
$var integer 32 z i [31:0] $end
$upscope $end
$upscope $end
$upscope $end
$upscope $end
$enddefinitions $end
#0
$dumpvars
bx z
bx y
bx x
bx w
bx v
bx u
bx t
bx s
bx r
bx q
bx p
bx o
bx n
bx m
bx l
bx k
bx j
bx i
bx h
bx g
bx f
bx e
bx d
bx c
bx b
bx a
bx `
bx _
bx ^
bx ]
bx \
bx [
bx Z
bx Y
bx X
bx W
bx V
bx U
bx T
bx S
bx R
xQ
bx P
bx O
bx N
xM
xL
xK
xJ
xI
xH
bx G
bx F
bx E
bx D
bx C
bx B
bx A
bx @
bx ?
bx >
bx =
bx <
bx ;
bx :
bx 9
bx 8
bx 7
b0xxxxxxxxxxxxxxxxxxxxxxxxxxxxxx 6
b0 5
b0 4
bx 3
bx 2
bx 1
b0xxxxxxxxxxxxxxxxxxxxxxxxxxxxxx 0
bx /
bx .
bx -
bx ,
x+
bx *
bx )
bx (
1'
b100 &
b0 %
b10000000000000000000000000000011 $
b0 #
0"
1!
$end
#5
0!
#10
b100 W
b100 p
b0 6
b0 y
b0 q
b100 E
b0 )
b0 7
b0 ;
b0 C
b0 r
b100000 z
1!
1"
#15
0!
#20
b100000000 @
b100000000 t
b100000000 D
b1000000 0
0H
b100000000 .
b100000000 1
b100000000 9
b100000000 G
b100000000 _
b100000000 e
b1 R
b1 b
b1 j
0L
0M
0+
0J
0Q
0K
b0 F
b0 f
b0 l
1I
b1 N
b1 k
b1 m
b0 S
b0 ^
b0 c
b0 P
b0 g
b0 [
b100000000 Z
b0 ]
b100000000 =
b100000000 X
b100 B
b0 -
b0 2
b0 T
b0 *
b0 /
b0 U
b10011 i
b0 h
b1000 a
b0 `
b0 Y
b0 ?
b0 \
b0 v
b0 u
b0 >
b0 x
b0 w
b1000 s
b0 d
b100000000 A
b100000000 O
b100000000 o
b10000000000000000010000010011 (
b10000000000000000010000010011 8
b10000000000000000010000010011 <
b10000000000000000010000010011 n
b1 q
b1 y
1!
0"
#25
0!
#30
b10 y
b10 q
1!
#35
0!
#40
b1000 B
b1000 W
b1000 p
b1 6
b100000100 A
b1000 E
b100 )
b100 7
b100 ;
b100 C
b100 r
b0 q
b0 y
1!
#45
0!
#50
b11111111111111111111111111111111 @
b11111111111111111111111111111111 t
b11111111111111111111111111111111 D
b111111111111111111111111111111 0
b11111111111111111111111111111111 .
b11111111111111111111111111111111 1
b11111111111111111111111111111111 9
b11111111111111111111111111111111 G
b11111111111111111111111111111111 _
b11111111111111111111111111111111 e
b11111111111111111111111111111111 Z
b11111111111111111111111111111111 =
b11111111111111111111111111111111 X
b1111111 a
b11111 w
b101 s
b11 A
b11111111111111111111111111111111 O
b11111111111111111111111111111111 o
b11111111111100000000001010010011 (
b11111111111100000000001010010011 8
b11111111111100000000001010010011 <
b11111111111100000000001010010011 n
b1 y
b1 q
1!
#55
0!
#60
b10 q
b10 y
1!
#65
0!
#70
b1100 B
b1100 W
b1100 p
b10 6
b0 y
b0 q
b111 A
b1100 E
b1000 )
b1000 7
b1000 ;
b1000 C
b1000 r
1!
#75
0!
#80
b110 s
b11111111111100000000001100010011 (
b11111111111100000000001100010011 8
b11111111111100000000001100010011 <
b11111111111100000000001100010011 n
b1 q
b1 y
1!
#85
0!
#90
b10 y
b10 q
1!
#95
0!
#100
b10000 B
b10000 W
b10000 p
b11 6
b1011 A
b10000 E
b1100 )
b1100 7
b1100 ;
b1100 C
b1100 r
b0 q
b0 y
1!
#105
0!
#110
b11111111111111111111111111111110 @
b11111111111111111111111111111110 t
b11111111111111111111111111111110 D
b111111111111111111111111111111 0
b0 R
b0 b
b0 j
1Q
b0 N
b0 k
b0 m
b11111111111111111111111111111110 .
b11111111111111111111111111111110 1
b11111111111111111111111111111110 9
b11111111111111111111111111111110 G
b11111111111111111111111111111110 _
b11111111111111111111111111111110 e
b11111111111111111111111111111111 Z
b11111111111111111111111111111111 =
b11111111111111111111111111111111 X
b111111110000000000000000 -
b111111110000000000000000 2
b111111110000000000000000 T
b110011 i
b0 a
b1111111111111111111111111111111000000000000000000000000000000001 ]
b1 [
b11111111111111111111111111111111 Y
b11111111111111111111111111111111 ?
b11111111111111111111111111111111 \
b11111111111111111111111111111111 v
b101 u
b11111111111111111111111111111111 >
b11111111111111111111111111111111 x
b110 w
b101 s
b1100 A
b0 O
b0 o
b11000101000001010110011 (
b11000101000001010110011 8
b11000101000001010110011 <
b11000101000001010110011 n
b1 y
b1 q
1!
#115
0!
#120
b10 q
b10 y
1!
#125
0!
